{
  "saleApps": [
    "com.financial.sdk.demo",
    "com.kozen.quickstartks",
    "tr.com.maxpay.ecom_mock",
    "tr.com.maxpay.tech_pos.maxpay",
    "com.faturamatik.pazar360",
    "com.faturamatik.takside",
    "com.faturamatik.tetas_pos",
    "com.faturamatik.ode_pos",
  ],
  "actions": [
    {
      "action": "android.settings.SETTINGS",
      "name": "Settings",
      "askPin": true
    },
    {
      "action": "android.settings.DATE_SETTINGS",
      "name": "Date & Time",
      "askPin": false
    },
    {
      "action": "android.settings.WIFI_SETTINGS",
      "name": "WiFi Settings",
      "askPin": true
    }
    
  ]
}
